<?xml version="1.0" encoding="UTF-8"?>
<MetaDataObject xmlns="http://v8.1c.ru/8.3/MDClasses" xmlns:app="http://v8.1c.ru/8.2/managed-application/core" xmlns:cfg="http://v8.1c.ru/8.1/data/enterprise/current-config" xmlns:cmi="http://v8.1c.ru/8.2/managed-application/cmi" xmlns:ent="http://v8.1c.ru/8.1/data/enterprise" xmlns:lf="http://v8.1c.ru/8.2/managed-application/logform" xmlns:style="http://v8.1c.ru/8.1/data/ui/style" xmlns:sys="http://v8.1c.ru/8.1/data/ui/fonts/system" xmlns:v8="http://v8.1c.ru/8.1/data/core" xmlns:v8ui="http://v8.1c.ru/8.1/data/ui" xmlns:web="http://v8.1c.ru/8.1/data/ui/colors/web" xmlns:win="http://v8.1c.ru/8.1/data/ui/colors/windows" xmlns:xen="http://v8.1c.ru/8.3/xcf/enums" xmlns:xpr="http://v8.1c.ru/8.3/xcf/predef" xmlns:xr="http://v8.1c.ru/8.3/xcf/readable" xmlns:xs="http://www.w3.org/2001/XMLSchema" xmlns:xsi="http://www.w3.org/2001/XMLSchema-instance" version="2.1">
	<Catalog uuid="b660d01f-9325-4f83-bf4d-8a574abb8a30">
		<InternalInfo>
			<xr:GeneratedType name="CatalogObject.ВидыВыплатЗарплаты" category="Object">
				<xr:TypeId>c94f332b-7ff9-4faa-83f5-f40d1c49e5d4</xr:TypeId>
				<xr:ValueId>635dc04a-58aa-4cf5-bc83-65d4a6ffb9bd</xr:ValueId>
			</xr:GeneratedType>
			<xr:GeneratedType name="CatalogRef.ВидыВыплатЗарплаты" category="Ref">
				<xr:TypeId>423859d5-df3d-4c65-aa08-8e7a796e1de0</xr:TypeId>
				<xr:ValueId>bd9039b2-b955-4773-9281-9785d426c344</xr:ValueId>
			</xr:GeneratedType>
			<xr:GeneratedType name="CatalogSelection.ВидыВыплатЗарплаты" category="Selection">
				<xr:TypeId>f24dac74-eb5f-4003-ac2e-fb78e9d0c51e</xr:TypeId>
				<xr:ValueId>b0399631-d1a2-4bd5-976e-dfd044d99491</xr:ValueId>
			</xr:GeneratedType>
			<xr:GeneratedType name="CatalogList.ВидыВыплатЗарплаты" category="List">
				<xr:TypeId>ed075d25-5249-43ff-ba99-45fbd855ec1e</xr:TypeId>
				<xr:ValueId>c4d8b17f-2327-4ab8-8304-0a91e9921029</xr:ValueId>
			</xr:GeneratedType>
			<xr:GeneratedType name="CatalogManager.ВидыВыплатЗарплаты" category="Manager">
				<xr:TypeId>1eba679e-28e9-4733-89b5-f59b41d2c478</xr:TypeId>
				<xr:ValueId>6c0abdf7-9fdd-470e-8fde-3831b31f4c9a</xr:ValueId>
			</xr:GeneratedType>
		</InternalInfo>
		<Properties>
			<Name>ВидыВыплатЗарплаты</Name>
			<Synonym>
				<v8:item>
					<v8:lang>ru</v8:lang>
					<v8:content>Виды выплат зарплаты</v8:content>
				</v8:item>
			</Synonym>
			<Comment/>
			<Hierarchical>false</Hierarchical>
			<HierarchyType>HierarchyFoldersAndItems</HierarchyType>
			<LimitLevelCount>false</LimitLevelCount>
			<LevelCount>2</LevelCount>
			<FoldersOnTop>true</FoldersOnTop>
			<UseStandardCommands>true</UseStandardCommands>
			<Owners/>
			<SubordinationUse>ToItems</SubordinationUse>
			<CodeLength>9</CodeLength>
			<DescriptionLength>25</DescriptionLength>
			<CodeType>String</CodeType>
			<CodeAllowedLength>Variable</CodeAllowedLength>
			<CodeSeries>WholeCatalog</CodeSeries>
			<CheckUnique>true</CheckUnique>
			<Autonumbering>true</Autonumbering>
			<DefaultPresentation>AsDescription</DefaultPresentation>
			<Characteristics/>
			<PredefinedDataUpdate>Auto</PredefinedDataUpdate>
			<EditType>InDialog</EditType>
			<QuickChoice>false</QuickChoice>
			<ChoiceMode>BothWays</ChoiceMode>
			<InputByString>
				<xr:Field>Catalog.ВидыВыплатЗарплаты.StandardAttribute.Description</xr:Field>
				<xr:Field>Catalog.ВидыВыплатЗарплаты.StandardAttribute.Code</xr:Field>
			</InputByString>
			<SearchStringModeOnInputByString>Begin</SearchStringModeOnInputByString>
			<FullTextSearchOnInputByString>DontUse</FullTextSearchOnInputByString>
			<ChoiceDataGetModeOnInputByString>Directly</ChoiceDataGetModeOnInputByString>
			<DefaultObjectForm/>
			<DefaultFolderForm/>
			<DefaultListForm/>
			<DefaultChoiceForm/>
			<DefaultFolderChoiceForm/>
			<AuxiliaryObjectForm/>
			<AuxiliaryFolderForm/>
			<AuxiliaryListForm/>
			<AuxiliaryChoiceForm/>
			<AuxiliaryFolderChoiceForm/>
			<IncludeHelpInContents>false</IncludeHelpInContents>
			<BasedOn/>
			<DataLockFields/>
			<DataLockControlMode>Managed</DataLockControlMode>
			<FullTextSearch>Use</FullTextSearch>
			<ObjectPresentation/>
			<ExtendedObjectPresentation/>
			<ListPresentation/>
			<ExtendedListPresentation/>
			<Explanation/>
			<CreateOnInput>Use</CreateOnInput>
			<ChoiceHistoryOnInput>Auto</ChoiceHistoryOnInput>
		</Properties>
		<ChildObjects/>
	</Catalog>
</MetaDataObject>