<?xml version="1.0" encoding="UTF-8"?>
<MetaDataObject xmlns="http://v8.1c.ru/8.3/MDClasses" xmlns:app="http://v8.1c.ru/8.2/managed-application/core" xmlns:cfg="http://v8.1c.ru/8.1/data/enterprise/current-config" xmlns:cmi="http://v8.1c.ru/8.2/managed-application/cmi" xmlns:ent="http://v8.1c.ru/8.1/data/enterprise" xmlns:lf="http://v8.1c.ru/8.2/managed-application/logform" xmlns:style="http://v8.1c.ru/8.1/data/ui/style" xmlns:sys="http://v8.1c.ru/8.1/data/ui/fonts/system" xmlns:v8="http://v8.1c.ru/8.1/data/core" xmlns:v8ui="http://v8.1c.ru/8.1/data/ui" xmlns:web="http://v8.1c.ru/8.1/data/ui/colors/web" xmlns:win="http://v8.1c.ru/8.1/data/ui/colors/windows" xmlns:xen="http://v8.1c.ru/8.3/xcf/enums" xmlns:xpr="http://v8.1c.ru/8.3/xcf/predef" xmlns:xr="http://v8.1c.ru/8.3/xcf/readable" xmlns:xs="http://www.w3.org/2001/XMLSchema" xmlns:xsi="http://www.w3.org/2001/XMLSchema-instance" version="2.1">
	<Enum uuid="5976f10f-56d0-4f88-b210-9a8fee1dba43">
		<InternalInfo>
			<xr:GeneratedType name="EnumRef.ТипыСтруктурныхЕдиниц" category="Ref">
				<xr:TypeId>2fbb2313-6533-494f-8445-e5a817e16f04</xr:TypeId>
				<xr:ValueId>5b5128a7-bca3-4850-b9f8-b438f3061bc6</xr:ValueId>
			</xr:GeneratedType>
			<xr:GeneratedType name="EnumManager.ТипыСтруктурныхЕдиниц" category="Manager">
				<xr:TypeId>8cbd2c54-f3ed-43ec-99af-1880d1c7ada3</xr:TypeId>
				<xr:ValueId>da6a80f2-451d-4a6f-92a4-c30f8d1995b4</xr:ValueId>
			</xr:GeneratedType>
			<xr:GeneratedType name="EnumList.ТипыСтруктурныхЕдиниц" category="List">
				<xr:TypeId>ba3ac1a3-fbe8-4069-9926-77dbb361c005</xr:TypeId>
				<xr:ValueId>466071fd-668f-49bb-83d4-422cd36f4759</xr:ValueId>
			</xr:GeneratedType>
		</InternalInfo>
		<Properties>
			<Name>ТипыСтруктурныхЕдиниц</Name>
			<Synonym>
				<v8:item>
					<v8:lang>ru</v8:lang>
					<v8:content>Типы структурных единиц</v8:content>
				</v8:item>
			</Synonym>
			<Comment/>
			<UseStandardCommands>true</UseStandardCommands>
			<StandardAttributes>
				<xr:StandardAttribute name="Order">
					<xr:LinkByType/>
					<xr:FillChecking>DontCheck</xr:FillChecking>
					<xr:MultiLine>false</xr:MultiLine>
					<xr:FillFromFillingValue>false</xr:FillFromFillingValue>
					<xr:CreateOnInput>Auto</xr:CreateOnInput>
					<xr:MaxValue xsi:nil="true"/>
					<xr:ToolTip/>
					<xr:ExtendedEdit>false</xr:ExtendedEdit>
					<xr:Format/>
					<xr:ChoiceForm/>
					<xr:QuickChoice>Auto</xr:QuickChoice>
					<xr:ChoiceHistoryOnInput>Auto</xr:ChoiceHistoryOnInput>
					<xr:EditFormat/>
					<xr:PasswordMode>false</xr:PasswordMode>
					<xr:MarkNegatives>false</xr:MarkNegatives>
					<xr:MinValue xsi:nil="true"/>
					<xr:Synonym/>
					<xr:Comment/>
					<xr:FullTextSearch>Use</xr:FullTextSearch>
					<xr:ChoiceParameterLinks/>
					<xr:FillValue xsi:nil="true"/>
					<xr:Mask/>
					<xr:ChoiceParameters/>
				</xr:StandardAttribute>
				<xr:StandardAttribute name="Ref">
					<xr:LinkByType/>
					<xr:FillChecking>DontCheck</xr:FillChecking>
					<xr:MultiLine>false</xr:MultiLine>
					<xr:FillFromFillingValue>false</xr:FillFromFillingValue>
					<xr:CreateOnInput>Auto</xr:CreateOnInput>
					<xr:MaxValue xsi:nil="true"/>
					<xr:ToolTip/>
					<xr:ExtendedEdit>false</xr:ExtendedEdit>
					<xr:Format/>
					<xr:ChoiceForm/>
					<xr:QuickChoice>Auto</xr:QuickChoice>
					<xr:ChoiceHistoryOnInput>Auto</xr:ChoiceHistoryOnInput>
					<xr:EditFormat/>
					<xr:PasswordMode>false</xr:PasswordMode>
					<xr:MarkNegatives>false</xr:MarkNegatives>
					<xr:MinValue xsi:nil="true"/>
					<xr:Synonym/>
					<xr:Comment/>
					<xr:FullTextSearch>Use</xr:FullTextSearch>
					<xr:ChoiceParameterLinks/>
					<xr:FillValue xsi:nil="true"/>
					<xr:Mask/>
					<xr:ChoiceParameters/>
				</xr:StandardAttribute>
			</StandardAttributes>
			<Characteristics/>
			<QuickChoice>true</QuickChoice>
			<ChoiceMode>BothWays</ChoiceMode>
			<DefaultListForm/>
			<DefaultChoiceForm/>
			<AuxiliaryListForm/>
			<AuxiliaryChoiceForm/>
			<ListPresentation/>
			<ExtendedListPresentation/>
			<Explanation/>
			<ChoiceHistoryOnInput>Auto</ChoiceHistoryOnInput>
		</Properties>
		<ChildObjects>
			<EnumValue uuid="a2c27200-4cab-457f-bfeb-49deb904531e">
				<Properties>
					<Name>Подразделение</Name>
					<Synonym>
						<v8:item>
							<v8:lang>ru</v8:lang>
							<v8:content>Подразделение</v8:content>
						</v8:item>
					</Synonym>
					<Comment/>
				</Properties>
			</EnumValue>
			<EnumValue uuid="f1cfda88-7c63-4e73-a54f-3c8db512fee9">
				<Properties>
					<Name>Склад</Name>
					<Synonym>
						<v8:item>
							<v8:lang>ru</v8:lang>
							<v8:content>Склад</v8:content>
						</v8:item>
					</Synonym>
					<Comment/>
				</Properties>
			</EnumValue>
			<EnumValue uuid="62720531-b286-4e83-b6ec-7a770484e1a7">
				<Properties>
					<Name>РозницаСуммовойУчет</Name>
					<Synonym>
						<v8:item>
							<v8:lang>ru</v8:lang>
							<v8:content>Розница (суммовой учет)</v8:content>
						</v8:item>
					</Synonym>
					<Comment/>
				</Properties>
			</EnumValue>
			<EnumValue uuid="9edb66ed-41e6-44d2-8219-9e288e2f016a">
				<Properties>
					<Name>Розница</Name>
					<Synonym>
						<v8:item>
							<v8:lang>ru</v8:lang>
							<v8:content>Розница</v8:content>
						</v8:item>
					</Synonym>
					<Comment/>
				</Properties>
			</EnumValue>
		</ChildObjects>
	</Enum>
</MetaDataObject>